django_safe_fields/__init__.py
django_safe_fields/fields.py
django_safe_fields/services.py
django_safe_fields/utils.py
django_safe_fields/management/__init__.py
django_safe_fields/management/commands/__init__.py
django_safe_fields/management/commands/list_safe_fields.py
django_safe_fields/management/commands/mapping_cipher_fields_dumps.py
django_safe_fields/migrations/__init__.py
django_safe_fields-0.2.3.dist-info/LICENSE
django_safe_fields-0.2.3.dist-info/METADATA
django_safe_fields-0.2.3.dist-info/WHEEL
django_safe_fields-0.2.3.dist-info/top_level.txt
django_safe_fields-0.2.3.dist-info/RECORD
