Metadata-Version: 2.1
Name: django-safe-fields
Version: 0.2.3
Summary: Save field value encrypted to database.
Author: rRR0VrFP
Maintainer: rRR0VrFP
License: MIT
Keywords: django extentions
Classifier: Development Status :: 5 - Production/Stable
Classifier: Intended Audience :: Developers
Classifier: Topic :: Software Development :: Libraries :: Python Modules
Classifier: License :: OSI Approved :: MIT License
Classifier: Programming Language :: Python :: 3
Classifier: Programming Language :: Python :: 3 :: Only
License-File: LICENSE
Requires-Dist: Django
Requires-Dist: fastutils
